myIMD_gauge/__init__.py
myIMD_gauge/myIMD_gauge.py
myIMD_gauge-0.0.7.dist-info/METADATA
myIMD_gauge-0.0.7.dist-info/WHEEL
myIMD_gauge-0.0.7.dist-info/top_level.txt
myIMD_gauge-0.0.7.dist-info/RECORD
